keyword_extract_LLM/__init__.py
keyword_extract_LLM/extractor.py
keyword_extract_LLM-1.0.5.dist-info/METADATA
keyword_extract_LLM-1.0.5.dist-info/WHEEL
keyword_extract_LLM-1.0.5.dist-info/top_level.txt
keyword_extract_LLM-1.0.5.dist-info/RECORD
