Metadata-Version: 2.1
Name: keyword-extract-LLM
Version: 1.0.5
Summary: using LLM to extract keywords
Home-page: https://github.com/Emekaborisama/keywordExtractorLLM
Author: Emeka Boris Ama
Author-email: borisphilosophy@gmail.com
License: MIT
Platform: UNKNOWN
Requires-Dist: setuptools (>=47.1.1)
Requires-Dist: torch
Requires-Dist: transformers
